{"DataType":"ThrottleDef","Version":"1.0","ProfName":"new profile","VMax":42,"AtStep":120,"SpeedSteps":128,"GraphData":{"DimX":"Speed Step","DimY":"km/h","mouseOverLine":-1,"Color":"rgb(150,150,250)","Width":3,"HLColor":"rgb(255,150,150)","ValsX":[0,127,10],"ValsY":[0,44.642533994999994,10],"Show":true,"DataElements":[{"x":0,"y":0,"m":0},{"x":12,"y":5,"m":0},{"x":24,"y":9,"m":0},{"x":36,"y":13,"m":0},{"x":48,"y":17,"m":0},{"x":60,"y":21,"m":0},{"x":72,"y":25,"m":0},{"x":84,"y":29,"m":0},{"x":96,"y":34,"m":0},{"x":108,"y":38,"m":0},{"x":120,"y":42,"m":0},{"x":126,"y":44.560498246302814,"m":0}]},"FileName":"SpeedProfile_60.json"}